browsers/__init__.py
browsers/common.py
browsers/linux.py
browsers/osx.py
browsers/py.typed
browsers/windows.py
pybrowsers-1.3.1.dist-info/LICENSE
pybrowsers-1.3.1.dist-info/METADATA
pybrowsers-1.3.1.dist-info/WHEEL
pybrowsers-1.3.1.dist-info/RECORD
