Metadata-Version: 2.3
Name: pybrowsers
Version: 1.3.1
Summary: Python library for detecting and launching browsers
License: MIT
Author: Ronie Martinez
Author-email: ronmarti18@gmail.com
Requires-Python: >=3.9
Classifier: Development Status :: 5 - Production/Stable
Classifier: License :: OSI Approved :: MIT License
Classifier: Topic :: Internet :: WWW/HTTP :: Browsers
Classifier: Topic :: Software Development :: Libraries :: Python Modules
Classifier: Programming Language :: Python :: 3
Classifier: Programming Language :: Python :: 3.9
Classifier: Programming Language :: Python :: 3.10
Classifier: Programming Language :: Python :: 3.11
Classifier: Programming Language :: Python :: 3.12
Classifier: Programming Language :: Python :: 3.13
Classifier: Programming Language :: Python :: Implementation :: CPython
Project-URL: Donate, https://github.com/sponsors/roniemartinez
Project-URL: Repository, https://github.com/roniemartinez/browsers
